models/__init__.py
models/_utils.py
models/alexnet.py
models/attention.py
models/attention_module.py
models/basic_layers.py
models/brain_humor.py
models/centerloss_resnet.py
models/densenet.py
models/fer2013_models.py
models/googlenet.py
models/grad_cam_resmaking.py
models/inception.py
models/inception_resnet_v1.py
models/masking.py
models/res_dense_gle.py
models/resatt.py
models/residual_attention_network.py
models/resmasking.py
models/resmasking_naive.py
models/resnet.py
models/resnet112.py
models/resnet50_scratch_dims_2048.py
models/runet.py
models/tmp.py
models/utils.py
models/vgg.py
models/segmentation/__init__.py
models/segmentation/_utils.py
models/segmentation/deeplabv3.py
models/segmentation/fcn.py
models/segmentation/segmentation.py
models/segmentation/unet_basic.py
rmn/__init__.py
rmn/version.py
rmn/configs/fer2013_config.json
rmn/models/__init__.py
rmn/models/_utils.py
rmn/models/alexnet.py
rmn/models/attention.py
rmn/models/attention_module.py
rmn/models/basic_layers.py
rmn/models/brain_humor.py
rmn/models/centerloss_resnet.py
rmn/models/densenet.py
rmn/models/fer2013_models.py
rmn/models/googlenet.py
rmn/models/grad_cam_resmaking.py
rmn/models/inception.py
rmn/models/inception_resnet_v1.py
rmn/models/masking.py
rmn/models/res_dense_gle.py
rmn/models/resatt.py
rmn/models/residual_attention_network.py
rmn/models/resmasking.py
rmn/models/resmasking_naive.py
rmn/models/resnet.py
rmn/models/resnet112.py
rmn/models/resnet50_scratch_dims_2048.py
rmn/models/runet.py
rmn/models/tmp.py
rmn/models/utils.py
rmn/models/vgg.py
rmn/models/segmentation/__init__.py
rmn/models/segmentation/_utils.py
rmn/models/segmentation/deeplabv3.py
rmn/models/segmentation/fcn.py
rmn/models/segmentation/segmentation.py
rmn/models/segmentation/unet_basic.py
utils/datasets/__init__.py
utils/datasets/affectnet_dataset.py
utils/datasets/ck_dataset.py
utils/datasets/fer2013dataset.py
utils/datasets/mixed_emotion.py
utils/datasets/mnist.py
utils/datasets/table_dataset.py
rmn-3.1.2.dist-info/LICENSE
rmn-3.1.2.dist-info/METADATA
rmn-3.1.2.dist-info/WHEEL
rmn-3.1.2.dist-info/top_level.txt
rmn-3.1.2.dist-info/RECORD
