Metadata-Version: 2.1
Name: rmn
Version: 3.1.2
Summary: Facial Expression Recognition using Residual Masking Network
Home-page: https://github.com/phamquiluan/ResidualMaskingNetwork
Author: Luan Pham
Author-email: phamquiluan@gmail.com
License-File: LICENSE
Requires-Dist: numpy
Requires-Dist: opencv-python
Requires-Dist: torch
Requires-Dist: torchvision
Requires-Dist: requests
Requires-Dist: pytorchcv
Requires-Dist: tqdm
